setup.cfg
setup.py
cw/__init__.py
cw/__listener__.py
cw/__sender__.py
cw/app.py
cw/messaging.py
cw/spark.py
lcmap_change_worker.egg-info/PKG-INFO
lcmap_change_worker.egg-info/SOURCES.txt
lcmap_change_worker.egg-info/dependency_links.txt
lcmap_change_worker.egg-info/entry_points.txt
lcmap_change_worker.egg-info/requires.txt
lcmap_change_worker.egg-info/top_level.txt
test/test_messaging.py