Metadata-Version: 1.1
Name: lcmap-change-worker
Version: 0.1.0
Summary: Module for executing change detection and sending results
Home-page: https://github.com/usgs-eros/lcmap-change-worker
Author: caustin-usgs
Author-email: clay.austin.ctr@usgs.gov
License: Public Domain
Keywords: python change detection rabbitmq cassandra
Platform: UNKNOWN
Classifier: Development Status :: 3 - Alpha
Classifier: Intended Audience :: Developers
Classifier: License :: Public Domain
Classifier: Programming Language :: Python :: 3
Classifier: Programming Language :: Python :: 3.4
Classifier: Programming Language :: Python :: 3.5
